agent_policy_engine-1.0.1.dist-info/licenses/LICENSE
ape/__init__.py
ape/config.py
ape/errors.py
ape/action/__init__.py
ape/action/action.py
ape/action/schema.json
ape/action_repository/__init__.py
ape/action_repository/repository.py
ape/action_repository/standard.py
ape/audit/__init__.py
ape/audit/logger.py
ape/authority/__init__.py
ape/authority/manager.py
ape/cli/__init__.py
ape/cli/main-orig.py
ape/cli/main.py
ape/enforcement/__init__.py
ape/enforcement/gate.py
ape/escalation/__init__.py
ape/escalation/handler.py
ape/intent/__init__.py
ape/intent/manager.py
ape/intent/schema.json
ape/intent_compiler/__init__.py
ape/intent_compiler/compiler.py
ape/mcp/__init__.py
ape/mcp/scanner.py
ape/orchestrator/__init__.py
ape/orchestrator/orchestrator.py
ape/plan/__init__.py
ape/plan/manager.py
ape/plan/schema.json
ape/plan_generator/__init__.py
ape/plan_generator/generator.py
ape/policy/__init__.py
ape/policy/engine.py
ape/policy/schema.json
ape/provenance/__init__.py
ape/provenance/manager.py
ape/reference_agent/__init__.py
ape/reference_agent/agent.py
ape/runtime/__init__.py
ape/runtime/orchestrator.py
ape/runtime/state.py
agent_policy_engine-1.0.1.dist-info/METADATA
agent_policy_engine-1.0.1.dist-info/WHEEL
agent_policy_engine-1.0.1.dist-info/entry_points.txt
agent_policy_engine-1.0.1.dist-info/top_level.txt
agent_policy_engine-1.0.1.dist-info/RECORD
