Metadata-Version: 2.4
Name: agent-policy-engine
Version: 1.0.1
Summary: Deterministic, capability-based policy enforcement runtime for AI agents
Author: Shawn Kahalewai Reilly
License: Apache-2.0
Project-URL: Homepage, https://github.com/kahalewai/agent-policy-engine
Project-URL: Documentation, https://github.com/kahalewai/agent-policy-engine/IMPLEMENTATION_GUIDE.md
Project-URL: Repository, https://github.com/kahalewai/agent-policy-engine
Project-URL: Changelog, https://github.com/kahalewai/agent-policy-engine/CHANGELOG.md
Keywords: ai,agents,security,policy,enforcement,llm,mcp,intent,orchestration
Classifier: Development Status :: 4 - Beta
Classifier: Intended Audience :: Developers
Classifier: License :: OSI Approved :: Apache Software License
Classifier: Programming Language :: Python :: 3
Classifier: Programming Language :: Python :: 3.10
Classifier: Programming Language :: Python :: 3.11
Classifier: Programming Language :: Python :: 3.12
Classifier: Topic :: Security
Classifier: Topic :: Software Development :: Libraries :: Python Modules
Classifier: Topic :: Scientific/Engineering :: Artificial Intelligence
Requires-Python: >=3.10
License-File: LICENSE
Requires-Dist: pyyaml>=6.0
Requires-Dist: jsonschema>=4.17.0
Provides-Extra: dev
Requires-Dist: pytest>=7.0; extra == "dev"
Requires-Dist: pytest-cov>=4.0; extra == "dev"
Requires-Dist: mypy>=1.0; extra == "dev"
Requires-Dist: ruff>=0.1.0; extra == "dev"
Dynamic: license-file
